debankpy/__init__.py
debankpy/connection.py
debankpy/const.py
debankpy/debank.py
debankpy/wallet.py
debankpy-0.0.7.dist-info/LICENSE
debankpy-0.0.7.dist-info/METADATA
debankpy-0.0.7.dist-info/WHEEL
debankpy-0.0.7.dist-info/top_level.txt
debankpy-0.0.7.dist-info/RECORD
