Metadata-Version: 2.1
Name: debankpy
Version: 0.0.7
Summary: Python library accessing Debank DeFi
Home-page: https://github.com/gtdiehl/debankpy
Author: Greg Diehl
Author-email: greg.diehl.gtd@gmail.com
License: UNKNOWN
Platform: UNKNOWN
Classifier: Programming Language :: Python :: 3
Classifier: License :: OSI Approved :: GNU General Public License v3 or later (GPLv3+)
Classifier: Operating System :: OS Independent
Requires-Python: >=3.8
License-File: LICENSE
Requires-Dist: httpx (==0.16.1)
